pymltools/__init__.py
pymltools/tf_utils/__init__.py
pymltools/tf_utils/basic_tools.py
pymltools/tf_utils/dataset_file_utils.py
pymltools/tf_utils/eval_utils.py
pymltools/tf_utils/init_hook_utils.py
pymltools/tf_utils/kaggle_voter_utils.py
pymltools/tf_utils/object_detection_utils.py
pymltools/tf_utils/path_utils.py
pymltools/tf_utils/pre_process_utils.py
pymltools/tf_utils/project_demo.py
pymltools/tf_utils/tf_board_utils.py
pymltools/tf_utils/tf_ckpt_utils.py
pymltools/tf_utils/tf_data_import.py
pymltools/tf_utils/tf_dataset.py
pymltools/tf_utils/tf_keras_utils.py
pymltools/tf_utils/tf_model_fn.py
pymltools/tf_utils/tf_optimizer.py
pymltools/tf_utils/tf_record_utils.py
pymltools/tf_utils/tf_visual_tools.py
pymltools/tf_utils/triplet_loss.py
test/__init__.py
test/test_eval_utils.py
test/test_np_utils.py
test/test_preprocess.py
test/test_tf_data_import.py
test/test_tf_func.py
pymltools-2019.2.17.dist-info/LICENSE
pymltools-2019.2.17.dist-info/METADATA
pymltools-2019.2.17.dist-info/WHEEL
pymltools-2019.2.17.dist-info/top_level.txt
pymltools-2019.2.17.dist-info/RECORD
