Metadata-Version: 2.1
Name: pymltools
Version: 2019.2.17
Summary: machine learning tools for python3.6
Home-page: https://github.com/frkhit/pymltools
Author: frkhit
Author-email: frkhit@gmail.com
License: MIT
Platform: UNKNOWN
Classifier: Development Status :: 4 - Beta
Classifier: Intended Audience :: Developers
Classifier: Intended Audience :: Other Audience
Classifier: Intended Audience :: Science/Research
Classifier: License :: OSI Approved :: MIT License
Classifier: Natural Language :: English
Classifier: Programming Language :: Python
Classifier: Programming Language :: Python :: 3.6
Classifier: Programming Language :: Python :: 3.7
Classifier: Topic :: Scientific/Engineering
Classifier: Topic :: Software Development :: Libraries
Classifier: Topic :: Utilities
Requires-Dist: tensorflow
Requires-Dist: pyxtools
Requires-Dist: h5py
Requires-Dist: numpy
Requires-Dist: Pillow
Requires-Dist: scikit-learn
Requires-Dist: SciPy
